torchtuples/__init__.py
torchtuples/_legacy_v1_1_0.py
torchtuples/base.py
torchtuples/callbacks.py
torchtuples/data.py
torchtuples/lr_scheduler.py
torchtuples/optim.py
torchtuples/practical.py
torchtuples/testing.py
torchtuples/tupletree.py
torchtuples/utils.py
torchtuples-0.2.2.dist-info/LICENSE
torchtuples-0.2.2.dist-info/METADATA
torchtuples-0.2.2.dist-info/WHEEL
torchtuples-0.2.2.dist-info/top_level.txt
torchtuples-0.2.2.dist-info/RECORD
