Metadata-Version: 2.1
Name: torchtuples
Version: 0.2.2
Summary: Training neural networks in PyTorch
Home-page: https://github.com/havakv/torchtuples
Author: Haavard Kvamme
Author-email: haavard.kvamme@gmail.com
License: BSD license
Keywords: torchtuples
Platform: UNKNOWN
Classifier: Development Status :: 2 - Pre-Alpha
Classifier: Intended Audience :: Developers
Classifier: License :: OSI Approved :: BSD License
Classifier: Natural Language :: English
Classifier: Programming Language :: Python :: 3.7
Classifier: Programming Language :: Python :: 3.6
Requires-Python: >=3.6
Requires-Dist: numpy (>=1.15.4)
Requires-Dist: pandas (>=0.24.2)
Requires-Dist: matplotlib (>=3.0.3)
